lit_tui/__init__.py
lit_tui/app.css
lit_tui/app.py
lit_tui/config.py
lit_tui/screens/__init__.py
lit_tui/screens/chat.py
lit_tui/screens/confirmation.py
lit_tui/screens/model_selection.py
lit_tui/screens/settings.py
lit_tui/services/__init__.py
lit_tui/services/conversation_logger.py
lit_tui/services/mcp_client.py
lit_tui/services/model_compatibility.py
lit_tui/services/ollama_client.py
lit_tui/services/prompt_composer.py
lit_tui/services/storage.py
lit_tui/services/tool_processor.py
lit_tui/widgets/__init__.py
lit_tui/widgets/input_field.py
lit_tui/widgets/message_list.py
lit_tui/widgets/sidebar.py
lit_tui-0.1.0.dist-info/licenses/LICENSE
lit_tui-0.1.0.dist-info/METADATA
lit_tui-0.1.0.dist-info/WHEEL
lit_tui-0.1.0.dist-info/entry_points.txt
lit_tui-0.1.0.dist-info/top_level.txt
lit_tui-0.1.0.dist-info/RECORD
