Metadata-Version: 2.4
Name: lit-tui
Version: 0.1.0
Summary: A lightweight terminal chat interface for Ollama with MCP integration
Author-email: Ben Vierck <ben@lit.ai>
License: MIT
Project-URL: Homepage, https://github.com/Positronic-AI/lit-tui
Project-URL: Documentation, https://github.com/Positronic-AI/lit-tui/blob/main/README.md
Project-URL: Repository, https://github.com/Positronic-AI/lit-tui
Project-URL: Issues, https://github.com/Positronic-AI/lit-tui/issues
Keywords: chat,ollama,tui,terminal,mcp,llm
Classifier: Development Status :: 3 - Alpha
Classifier: Environment :: Console
Classifier: Intended Audience :: Developers
Classifier: License :: OSI Approved :: MIT License
Classifier: Operating System :: OS Independent
Classifier: Programming Language :: Python :: 3
Classifier: Programming Language :: Python :: 3.8
Classifier: Programming Language :: Python :: 3.9
Classifier: Programming Language :: Python :: 3.10
Classifier: Programming Language :: Python :: 3.11
Classifier: Programming Language :: Python :: 3.12
Classifier: Topic :: Communications :: Chat
Classifier: Topic :: Scientific/Engineering :: Artificial Intelligence
Requires-Python: >=3.8
License-File: LICENSE
Requires-Dist: textual>=0.40.0
Requires-Dist: rich>=13.0.0
Requires-Dist: ollama>=0.4.0
Requires-Dist: aiofiles>=23.0.0
Requires-Dist: pydantic>=2.0.0
Requires-Dist: asyncio-mqtt>=0.13.0
Provides-Extra: dev
Requires-Dist: pytest>=7.0.0; extra == "dev"
Requires-Dist: pytest-asyncio>=0.21.0; extra == "dev"
Requires-Dist: black>=23.0.0; extra == "dev"
Requires-Dist: isort>=5.12.0; extra == "dev"
Requires-Dist: mypy>=1.0.0; extra == "dev"
Requires-Dist: pre-commit>=3.0.0; extra == "dev"
Provides-Extra: mcp
Requires-Dist: mcp>=1.0.0; extra == "mcp"
Provides-Extra: enhanced
Requires-Dist: system-prompt-composer>=1.0.0; extra == "enhanced"
Dynamic: license-file
